django_simple_deploy/__init__.py
django_simple_deploy/apps.py
django_simple_deploy/hookspecs.py
django_simple_deploy/plugins.py
django_simple_deploy/django_simple_deploy.egg-info/PKG-INFO
django_simple_deploy/django_simple_deploy.egg-info/SOURCES.txt
django_simple_deploy/django_simple_deploy.egg-info/dependency_links.txt
django_simple_deploy/django_simple_deploy.egg-info/requires.txt
django_simple_deploy/django_simple_deploy.egg-info/top_level.txt
django_simple_deploy/management/__init__.py
django_simple_deploy/management/commands/__init__.py
django_simple_deploy/management/commands/cli.py
django_simple_deploy/management/commands/deploy.py
django_simple_deploy/management/commands/dsd_messages.py
django_simple_deploy/management/commands/utils/__init__.py
django_simple_deploy/management/commands/utils/command_errors.py
django_simple_deploy/management/commands/utils/dsd_config.py
django_simple_deploy/management/commands/utils/dsd_utils.py
django_simple_deploy/management/commands/utils/plugin_utils.py
django_simple_deploy-1.4.0.dist-info/licenses/LICENSE
django_simple_deploy-1.4.0.dist-info/METADATA
django_simple_deploy-1.4.0.dist-info/WHEEL
django_simple_deploy-1.4.0.dist-info/top_level.txt
django_simple_deploy-1.4.0.dist-info/RECORD
