Metadata-Version: 2.4
Name: django-simple-deploy
Version: 1.4.0
Summary: Deployment, for Djangonauts with deadlines.
Author-email: Eric Matthes <ehmatthes@gmail.com>
Project-URL: Documentation, https://django-simple-deploy.readthedocs.io/en/latest/
Project-URL: GitHub, https://github.com/django-simple-deploy/django-simple-deploy
Project-URL: Changelog, https://github.com/django-simple-deploy/django-simple-deploy/blob/main/CHANGELOG.md
Keywords: django,deployment
Classifier: Development Status :: 4 - Beta
Classifier: Framework :: Django :: 4.2
Classifier: Framework :: Django :: 5.0
Classifier: Framework :: Django :: 5.1
Classifier: Intended Audience :: Developers
Classifier: License :: OSI Approved :: BSD License
Classifier: Operating System :: OS Independent
Classifier: Programming Language :: Python :: 3 :: Only
Classifier: Programming Language :: Python :: 3.9
Classifier: Programming Language :: Python :: 3.10
Classifier: Programming Language :: Python :: 3.11
Classifier: Programming Language :: Python :: 3.12
Classifier: Programming Language :: Python :: 3.13
Requires-Python: >=3.9
License-File: LICENSE
Requires-Dist: django>=4.2
Requires-Dist: pluggy>=1.5.0
Requires-Dist: toml>=0.10.2
Requires-Dist: requests>=2.32.2
Provides-Extra: fly-io
Requires-Dist: dsd-flyio; extra == "fly-io"
Provides-Extra: upsun
Requires-Dist: dsd-upsun; extra == "upsun"
Provides-Extra: heroku
Requires-Dist: dsd-heroku; extra == "heroku"
Provides-Extra: dev
Requires-Dist: black>=24.1.0; extra == "dev"
Requires-Dist: build>=1.2.1; extra == "dev"
Requires-Dist: mkdocs>=1.6.0; extra == "dev"
Requires-Dist: mkdocs-material>=9.5.0; extra == "dev"
Requires-Dist: mkdocstrings-python>=1.13.0; extra == "dev"
Requires-Dist: pipenv>=2024.4.0; extra == "dev"
Requires-Dist: pytest>=8.3.0; extra == "dev"
Requires-Dist: twine>=5.1.1; extra == "dev"
Dynamic: license-file
